
  [
    {
      "firstname": "Aditi",
      "lastname": "Rajput",
      "license": "BLR3344556677",
      "location" : {
        "coordinates": [77.5875, 12.9790]
      }
    },
    {
      "firstname": "Amitabh",
      "lastname": "Sharma",
      "license": "BLR4455667788",
      "location" : {
        "coordinates": [77.5874, 12.9791]
      }
    },
    {
      "firstname": "Shweta",
      "lastname": "Nair",
      "license": "BLR5566778899",
      "location" : {
        "coordinates": [77.5873, 12.9792]
      }
    },
    {
      "firstname": "Ravi",
      "lastname": "Menon",
      "license": "BLR6677889900",
      "location" : {
        "coordinates": [77.5872, 12.9793]
      }
    },
    {
      "firstname": "Meenakshi",
      "lastname": "Rao",
      "license": "BLR7788990011",
      "location" : {
        "coordinates": [77.5871, 12.9794]
      }
    },
    {
      "firstname": "Siddharth",
      "lastname": "Kumar",
      "license": "BLR8899001122",
      "location" : {
        "coordinates": [77.5870, 12.9795]
      }
    },
    {
      "firstname": "Kavita",
      "lastname": "Iyer",
      "license": "BLR9900112233",
      "location" : {
        "coordinates": [77.5869, 12.9796]
      }
    },
    {
      "firstname": "Rajesh",
      "lastname": "Shah",
      "license": "BLR0011223344",
      "location" : {
        "coordinates": [77.5868, 12.9797]
      }
    },
    {
      "firstname": "Nivedita",
      "lastname": "Menon",
      "license": "BLR1122334455",
      "location" : {
        "coordinates": [77.5867, 12.9798]
      }
    },
    {
      "firstname": "Arun",
      "lastname": "Rastogi",
      "license": "BLR2233445566",
      "location" : {
        "coordinates": [77.5866, 12.9799]
      }
    },
    {
      "firstname": "Mukesh",
      "lastname": "Singh",
      "license": "BLR3344556677",
      "location" : {
        "coordinates": [77.5865, 12.9800]
      }
    },
    {
      "firstname": "Neha",
      "lastname": "Patel",
      "license": "BLR4455667788",
      "location" : {
        "coordinates": [77.5864, 12.9801]
      }
    },
    {
      "firstname": "Rahul",
      "lastname": "Shetty",
      "license": "BLR5566778899",
      "location" : {
        "coordinates": [77.5863, 12.9802]
      }
    },
    {
      "firstname": "Sonia",
      "lastname": "Iyer",
      "license": "BLR6677889900",
      "location" : {
        "coordinates": [77.5862, 12.9803]
      }
    },
    {
      "firstname": "Vikas",
      "lastname": "Menon",
      "license": "BLR7788990011",
      "location" : {
        "coordinates": [77.5861, 12.9804]
      }
    },
    {
      "firstname": "Anjali",
      "lastname": "Patil",
      "license": "BLR8899001122",
      "location" : {
        "coordinates": [77.5860, 12.9805]
      }
    },
    {
      "firstname": "Alok",
      "lastname": "Raj",
      "license": "BLR9900112233",
      "location" : {
        "coordinates": [77.5859, 12.9806]
      }
    },
    {
      "firstname": "Pallavi",
      "lastname": "Sharma",
      "license": "BLR0011223344",
      "location" : {
        "coordinates": [77.5858, 12.9807]
      }
    },
    {
      "firstname": "Vivek",
      "lastname": "Naidu",
      "license": "BLR1122334455",
      "location" : {
        "coordinates": [77.5857, 12.9808]
      }
    },
    {
      "firstname": "Ananya",
      "lastname": "Kumar",
      "license": "BLR2233445566",
      "location" : {
        "coordinates": [77.5856, 12.9809]
      }
    },
    {
      "firstname": "Nandini",
      "lastname": "Sharma",
      "license": "BLR3344556677",
      "location" : {
        "coordinates": [77.5855, 12.9810]
      }
    },
    {
      "firstname": "Arjun",
      "lastname": "Nair",
      "license": "BLR4455667788",
      "location" : {
        "coordinates": [77.5854, 12.9811]
      }
    },
    {
      "firstname": "Shreya",
      "lastname": "Menon",
      "license": "BLR5566778899",
      "location" : {
        "coordinates": [77.5853, 12.9812]
      }
    },
    {
      "firstname": "Praveen",
      "lastname": "Shah",
      "license": "BLR6677889900",
      "location" : {
        "coordinates": [77.5852, 12.9813]
      }
    },
    {
      "firstname": "Nisha",
      "lastname": "Iyer",
      "license": "BLR7788990011",
      "location" : {
        "coordinates": [77.5851, 12.9814]
      }
    },
    {
      "firstname": "Rajiv",
      "lastname": "Rao",
      "license": "BLR8899001122",
      "location" : {
        "coordinates": [77.5850, 12.9815]
      }
    },
    {
      "firstname": "Sangeetha",
      "lastname": "Kumar",
      "license": "BLR9900112233",
      "location" : {
        "coordinates": [77.5849, 12.9816]
      }
    },
    {
      "firstname": "Ramesh",
      "lastname": "Menon",
      "license": "BLR0011223344",
      "location" : {
        "coordinates": [77.5848, 12.9817]
      }
    },
    {
      "firstname": "Sunita",
      "lastname": "Sharma",
      "license": "BLR1122334455",
      "location" : {
        "coordinates": [77.5847, 12.9818]
      }
    },
    {
      "firstname": "Anand",
      "lastname": "Narayan",
      "license": "BLR3344556677",
      "location" : {
        "coordinates": [77.5895, 12.9770]
      }
    },
    {
      "firstname": "Shivani",
      "lastname": "Kulkarni",
      "license": "BLR4455667788",
      "location" : {
        "coordinates": [77.5894, 12.9771]
      }
    },
    {
      "firstname": "Rajendra",
      "lastname": "Sharma",
      "license": "BLR5566778899",
      "location" : {
        "coordinates": [77.5893, 12.9772]
      }
    },
    {
      "firstname": "Anusha",
      "lastname": "Rao",
      "license": "BLR6677889900",
      "location" : {
        "coordinates": [77.5892, 12.9773]
      }
    },
    {
      "firstname": "Rohini",
      "lastname": "Gowda",
      "license": "BLR7788990011",
      "location" : {
        "coordinates": [77.5891, 12.9774]
      }
    },
    {
      "firstname": "Avinash",
      "lastname": "Patil",
      "license": "BLR8899001122",
      "location" : {
        "coordinates": [77.5890, 12.9775]
      }
    },
    {
      "firstname": "Kiran",
      "lastname": "Iyer",
      "license": "BLR9900112233",
      "location" : {
        "coordinates": [77.5889, 12.9776]
      }
    },
    {
      "firstname": "Anjali",
      "lastname": "Shah",
      "license": "BLR0011223344",
      "location" : {
        "coordinates": [77.5888, 12.9777]
      }
    },
    {
      "firstname": "Sanjay",
      "lastname": "Menon",
      "license": "BLR1122334455",
      "location" : {
        "coordinates": [77.5887, 12.9778]
      }
    },
    {
      "firstname": "Mala",
      "lastname": "Rastogi",
      "license": "BLR2233445566",
      "location" : {
        "coordinates": [77.5886, 12.9779]
      }
    },
    {
      "firstname": "Nikhil",
      "lastname": "Singh",
      "license": "BLR3344556677",
      "location" : {
        "coordinates": [77.5885, 12.9780]
      }
    },
    {
      "firstname": "Priyanka",
      "lastname": "Nair",
      "license": "BLR4455667788",
      "location" : {
        "coordinates": [77.5884, 12.9781]
      }
    },
    {
      "firstname": "Rajiv",
      "lastname": "Sharma",
      "license": "BLR5566778899",
      "location" : {
        "coordinates": [77.5883, 12.9782]
      }
    },
    {
      "firstname": "Ananya",
      "lastname": "Iyer",
      "license": "BLR6677889900",
      "location" : {
        "coordinates": [77.5882, 12.9783]
      }
    },
    {
      "firstname": "Vikram",
      "lastname": "Menon",
      "license": "BLR7788990011",
      "location" : {
        "coordinates": [77.5881, 12.9784]
      }
    },
    {
      "firstname": "Sneha",
      "lastname": "Patel",
      "license": "BLR8899001122",
      "location" : {
        "coordinates": [77.5880, 12.9785]
      }
    },
    {
      "firstname": "Amit",
      "lastname": "Raj",
      "license": "BLR9900112233",
      "location" : {
        "coordinates": [77.5879, 12.9786]
      }
    },
    {
      "firstname": "Pooja",
      "lastname": "Shetty",
      "license": "BLR0011223344",
      "location" : {
        "coordinates": [77.5878, 12.9787]
      }
    },
    {
      "firstname": "Rahul",
      "lastname": "Naidu",
      "license": "BLR1122334455",
      "location" : {
        "coordinates": [77.5877, 12.9788]
      }
    },
    {
      "firstname": "Sangeeta",
      "lastname": "Kumar",
      "license": "BLR2233445566",
      "location" : {
        "coordinates": [77.5876, 12.9789]
      }
    },
    {
      "firstname": "Sneha",
      "lastname": "Raj",
      "license": "BLR1122334455",
      "location" : {
        "coordinates": [77.5915, 12.9750]
      }
    },
    {
      "firstname": "Kiran",
      "lastname": "Shah",
      "license": "BLR2233445566",
      "location" : {
        "coordinates": [77.5914, 12.9751]
      }
    },
    {
      "firstname": "Neha",
      "lastname": "Iyer",
      "license": "BLR3344556677",
      "location" : {
        "coordinates": [77.5913, 12.9752]
      }
    },
    {
      "firstname": "Vishal",
      "lastname": "Menon",
      "license": "BLR4455667788",
      "location" : {
        "coordinates": [77.5912, 12.9753]
      }
    },
    {
      "firstname": "Ananya",
      "lastname": "Rao",
      "license": "BLR5566778899",
      "location" : {
        "coordinates": [77.5911, 12.9754]
      }
    },
    {
      "firstname": "Rajiv",
      "lastname": "Kumar",
      "license": "BLR6677889900",
      "location" : {
        "coordinates": [77.5910, 12.9755]
      }
    },
    {
      "firstname": "Preeti",
      "lastname": "Sinha",
      "license": "BLR7788990011",
      "location" : {
        "coordinates": [77.5909, 12.9756]
      }
    },
    {
      "firstname": "Aryan",
      "lastname": "Gowda",
      "license": "BLR8899001122",
      "location" : {
        "coordinates": [77.5908, 12.9757]
      }
    },
    {
      "firstname": "Rohit",
      "lastname": "Patel",
      "license": "BLR9900112233",
      "location" : {
        "coordinates": [77.5907, 12.9758]
      }
    },
    {
      "firstname": "Shweta",
      "lastname": "Nair",
      "license": "BLR0011223344",
      "location" : {
        "coordinates": [77.5906, 12.9759]
      }
    },
    {
      "firstname": "Aditya",
      "lastname": "Sharma",
      "license": "BLR1122334455",
      "location" : {
        "coordinates": [77.5905, 12.9760]
      }
    },
    {
      "firstname": "Divakar",
      "lastname": "Kannan",
      "license": "BLR2233445566",
      "location" : {
        "coordinates": [77.5904, 12.9761]
      }
    },
    {
      "firstname": "Shreya",
      "lastname": "Rastogi",
      "license": "BLR3344556677",
      "location" : {
        "coordinates": [77.5903, 12.9762]
      }
    },
    {
      "firstname": "Karthik",
      "lastname": "Sinha",
      "license": "BLR4455667788",
      "location" : {
        "coordinates": [77.5902, 12.9763]
      }
    },
    {
      "firstname": "Nisha",
      "lastname": "Prasad",
      "license": "BLR5566778899",
      "location" : {
        "coordinates": [77.5901, 12.9764]
      }
    },
    {
      "firstname": "Rajesh",
      "lastname": "Iyer",
      "license": "BLR6677889900",
      "location" : {
        "coordinates": [77.5900, 12.9765]
      }
    },
    {
      "firstname": "Deepa",
      "lastname": "Menon",
      "license": "BLR7788990011",
      "location" : {
        "coordinates": [77.5899, 12.9766]
      }
    },
    {
      "firstname": "Ravi",
      "lastname": "Rajput",
      "license": "BLR8899001122",
      "location" : {
        "coordinates": [77.5898, 12.9767]
      }
    },
    {
      "firstname": "Kavitha",
      "lastname": "Reddy",
      "license": "BLR9900112233",
      "location" : {
        "coordinates": [77.5897, 12.9768]
      }
    },
    {
      "firstname": "Aruna",
      "lastname": "Shetty",
      "license": "BLR0011223344",
      "location" : {
        "coordinates": [77.5896, 12.9769]
      }
    },
    {
      "firstname": "Amit",
      "lastname": "Gupta",
      "license": "BLR1234567890",
      "location" : {
        "coordinates": [77.5935, 12.9727]
      }
    },
    {
      "firstname": "Kavita",
      "lastname": "Nair",
      "license": "BLR2345678901",
      "location" : {
        "coordinates": [77.5934, 12.9728]
      }
    },
    {
      "firstname": "Suresh",
      "lastname": "Kulkarni",
      "license": "BLR3456789012",
      "location" : {
        "coordinates": [77.5933, 12.9729]
      }
    },
    {
      "firstname": "Pooja",
      "lastname": "Rajput",
      "license": "BLR4567890123",
      "location" : {
        "coordinates": [77.5932, 12.9730]
      }
    },
    {
      "firstname": "Sanjay",
      "lastname": "Pillai",
      "license": "BLR5678901234",
      "location" : {
        "coordinates": [77.5931, 12.9731]
      }
    },
    {
      "firstname": "Rekha",
      "lastname": "Gowda",
      "license": "BLR6789012345",
      "location" : {
        "coordinates": [77.5930, 12.9732]
      }
    },
    {
      "firstname": "Rajesh",
      "lastname": "Shetty",
      "license": "BLR7890123456",
      "location" : {
        "coordinates": [77.5929, 12.9733]
      }
    },
    {
      "firstname": "Deepak",
      "lastname": "Malhotra",
      "license": "BLR8901234567",
      "location" : {
        "coordinates": [77.5928, 12.9734]
      }
    },
    {
      "firstname": "Shilpa",
      "lastname": "Rao",
      "license": "BLR9012345678",
      "location" : {
        "coordinates": [77.5927, 12.9735]
      }
    },
    {
      "firstname": "Vivek",
      "lastname": "Iyer",
      "license": "BLR0123456789",
      "location" : {
        "coordinates": [77.5926, 12.9736]
      }
    },
    {
      "firstname": "Manoj",
      "lastname": "Rastogi",
      "license": "BLR1234567890",
      "location" : {
        "coordinates": [77.5925, 12.9737]
      }
    },
    {
      "firstname": "Anita",
      "lastname": "Kannan",
      "license": "BLR2345678901",
      "location" : {
        "coordinates": [77.5924, 12.9738]
      }
    },
    {
      "firstname": "Harish",
      "lastname": "Sinha",
      "license": "BLR3456789012",
      "location" : {
        "coordinates": [77.5923, 12.9739]
      }
    },
    {
      "firstname": "Rohini",
      "lastname": "Menon",
      "license": "BLR4567890123",
      "location" : {
        "coordinates": [77.5922, 12.9740]
      }
    },
    {
      "firstname": "Gaurav",
      "lastname": "Prasad",
      "license": "BLR5678901234",
      "location" : {
        "coordinates": [77.5921, 12.9741]
      }
    },
    {
      "firstname": "Jyoti",
      "lastname": "Nayar",
      "license": "BLR6789012345",
      "location" : {
        "coordinates": [77.5920, 12.9742]
      }
    },
    {
      "firstname": "Arun",
      "lastname": "Pai",
      "license": "BLR7890123456",
      "location" : {
        "coordinates": [77.5919, 12.9743]
      }
    },
    {
      "firstname": "Varun",
      "lastname": "Das",
      "license": "BLR8901234567",
      "location" : {
        "coordinates": [77.5918, 12.9744]
      }
    },
    {
      "firstname": "Shalini",
      "lastname": "Menon",
      "license": "BLR9012345678",
      "location" : {
        "coordinates": [77.5917, 12.9745]
      }
    },
    {
      "firstname": "Vinod",
      "lastname": "Sharma",
      "license": "BLR0123456789",
      "location" : {
        "coordinates": [77.5916, 12.9746]
      }
    },
    {
      "firstname": "Rahul",
      "lastname": "Kumar",
      "license": "BLR1234567890",
      "location" : {
        "coordinates": [77.5946, 12.9716]
      }
    },
    {
      "firstname": "Priya",
      "lastname": "Sharma",
      "license": "BLR2345678901",
      "location" : {
        "coordinates": [77.5944, 12.9718]
      }
    },
    {
      "firstname": "Arjun",
      "lastname": "Singh",
      "license": "BLR3456789012",
      "location" : {
        "coordinates": [77.5943, 12.9719]
      }
    },
    {
      "firstname": "Anjali",
      "lastname": "Patel",
      "license": "BLR4567890123",
      "location" : {
        "coordinates": [77.5942, 12.9720]
      }
    },
    {
      "firstname": "Vikram",
      "lastname": "Reddy",
      "license": "BLR5678901234",
      "location" : {
        "coordinates": [77.5941, 12.9721]
      }
    },
    {
      "firstname": "Nisha",
      "lastname": "Menon",
      "license": "BLR6789012345",
      "location" : {
        "coordinates": [77.5940, 12.9722]
      }
    },
    {
      "firstname": "Siddharth",
      "lastname": "Rao",
      "license": "BLR7890123456",
      "location" : {
        "coordinates": [77.5939, 12.9723]
      }
    },
    {
      "firstname": "Meera",
      "lastname": "Iyer",
      "license": "BLR8901234567",
      "location" : {
        "coordinates": [77.5938, 12.9724]
      }
    },
    {
      "firstname": "Ajay",
      "lastname": "Desai",
      "license": "BLR9012345678",
      "location" : {
        "coordinates": [77.5937, 12.9725]
      }
    },
    {
      "firstname": "Divya",
      "lastname": "Naidu",
      "license": "BLR0123456789",
      "location" : {
        "coordinates": [77.5936, 12.9726]
      }
    }
  ]

